wpexam/__init__.py
wpexam/systeminfo.py
wpexam/exam.py
WPExam-1.0.0.dist-info/DESCRIPTION.rst
WPExam-1.0.0.dist-info/RECORD
WPExam-1.0.0.dist-info/metadata.json
WPExam-1.0.0.dist-info/WHEEL
WPExam-1.0.0.dist-info/top_level.txt
WPExam-1.0.0.dist-info/METADATA
