Metadata-Version: 2.0
Name: WPExam
Version: 1.0.0
Summary: creation of pre-populated exam locations
Home-page: https://github.com/nharringtonwasatch/WPExam
Author: Nathan Harrington
Author-email: nharrington@wasatchphotonics.com
License: UNKNOWN
Download-URL: https://github.com/nharringtonwasatch/WPExam
Platform: UNKNOWN
